## 类加载&对象初始化

### 子类&父类

```java
class Parent {

    static {
        System.out.println("父类静态代码块");
    }

    public Parent() {
        System.out.println("父类构造方法");
    }

}

class Children extends Parent {

    static {
        System.out.println("子类静态代码块");
    }

    public Children() {
        System.out.println("子类构造方法");
    }

}

public class Test {

    public static void main(String[] args) {
        new Children();
    }

}
```

***输出***

```console
父类静态代码块
子类静态代码块
父类构造方法
子类构造方法
```

### 加载&初始化

```java
class Instance {

    static {
        System.out.println("静态代码块1");
    }

    // 静态变量，在类加载初始化阶段赋值
    public static int i = 1;
    // 静态基本类型常量，在类加载准备阶段赋值
    public static final int j = 1;
    // 静态引用类型常量，在类加载初始化阶段赋值
    public static final Temp k = new Temp("静态引用类型常量");

    static {
        System.out.println("静态代码块2");
    }

    {
        System.out.println("构造代码块1");
    }

    private Temp m = new Temp("成员变量");

    public Instance() {
        System.out.println("构造方法");
    }

    {
        System.out.println("构造代码块2");
    }

}

class Temp {

    public Temp(String name) {
        System.out.println(name);
    }

}

public class Test {

    public static void main(String[] args) {
        new Instance();
    }

}
```

***输出***

```console
静态代码块1
静态引用类型常量
静态代码块2
构造代码块1
成员变量
构造代码块2
构造方法
```

反编译: ```javap -v Instance.class```

```java
public test.Instance();
  descriptor: ()V
  flags: ACC_PUBLIC
  Code:
    stack=4, locals=1, args_size=1
       0: aload_0
       1: invokespecial #1                  // Method java/lang/Object."<init>":()V
       4: getstatic     #2                  // Field java/lang/System.out:Ljava/io/PrintStream;
       7: ldc           #3                  // String 构造代码块1
       9: invokevirtual #4                  // Method java/io/PrintStream.println:(Ljava/lang/String;)V
      12: aload_0
      13: new           #5                  // class test/Temp
      16: dup
      17: ldc           #6                  // String 成员变量
      19: invokespecial #7                  // Method test/Temp."<init>":(Ljava/lang/String;)V
      22: putfield      #8                  // Field m:Ltest/Temp;
      25: getstatic     #2                  // Field java/lang/System.out:Ljava/io/PrintStream;
      28: ldc           #9                  // String 构造代码块2
      30: invokevirtual #4                  // Method java/io/PrintStream.println:(Ljava/lang/String;)V
      33: getstatic     #2                  // Field java/lang/System.out:Ljava/io/PrintStream;
      36: ldc           #10                 // String 构造方法
      38: invokevirtual #4                  // Method java/io/PrintStream.println:(Ljava/lang/String;)V

static {};
  descriptor: ()V
  flags: ACC_STATIC
  Code:
    stack=3, locals=0, args_size=0
       0: getstatic     #2                  // Field java/lang/System.out:Ljava/io/PrintStream;
       3: ldc           #11                 // String 静态代码块1
       5: invokevirtual #4                  // Method java/io/PrintStream.println:(Ljava/lang/String;)V
       8: iconst_1
       9: putstatic     #12                 // Field i:I
      12: new           #5                  // class test/Temp
      15: dup
      16: ldc           #13                 // String 静态引用类型常量
      18: invokespecial #7                  // Method test/Temp."<init>":(Ljava/lang/String;)V
      21: putstatic     #14                 // Field k:Ltest/Temp;
      24: getstatic     #2                  // Field java/lang/System.out:Ljava/io/PrintStream;
      27: ldc           #15                 // String 静态代码块2
      29: invokevirtual #4                  // Method java/io/PrintStream.println:(Ljava/lang/String;)V
      32: return
```

#### <cinit\>方法

> 静态代码块、静态变量、静态引用类型常量按声明顺序执行

#### <init\>方法

> 构造代码块、成员变量按声明顺序执行，然后执行构造方法

### 总结

综上所述，类加载和对象初始化的过程:

***类加载***

* `父类准备阶段`: 加载父类，给父类静态变量分配内存空间，并给父类静态基本类型常量赋值
* `父类初始化阶段`: 父类静态代码块、静态变量、静态引用类型常量按声明顺序执行
* `子类准备阶段`: 加载子类，给子类静态变量分配内存空间，并给子类静态基本类型常量赋值
* `子类初始化阶段`: 子类静态代码块、静态变量、静态引用类型常量按声明顺序执行

***对象初始化***

* 给对象分配内存空间
* 父类构造代码块、成员变量按声明顺序执行
* 父类构造方法
* 子类构造代码块、成员变量按声明顺序执行
* 子类构造方法
